psutil_wheels-5.8.0.dist-info/METADATA
psutil_wheels-5.8.0.dist-info/RECORD
psutil_wheels-5.8.0.dist-info/LICENSE
psutil_wheels-5.8.0.dist-info/WHEEL
psutil_wheels-5.8.0.dist-info/top_level.txt
psutil/_psposix.py
psutil/_compat.py
psutil/_psutil_linux.cpython-39-x86_64-linux-gnu.so
psutil/__init__.py
psutil/_psutil_posix.cpython-39-x86_64-linux-gnu.so
psutil/_common.py
psutil/_psosx.py
psutil/_psbsd.py
psutil/_psaix.py
psutil/_pswindows.py
psutil/_pslinux.py
psutil/_pssunos.py
psutil/tests/test_windows.py
psutil/tests/test_system.py
psutil/tests/test_aix.py
psutil/tests/test_misc.py
psutil/tests/test_posix.py
psutil/tests/__init__.py
psutil/tests/test_osx.py
psutil/tests/test_unicode.py
psutil/tests/test_connections.py
psutil/tests/test_bsd.py
psutil/tests/test_sunos.py
psutil/tests/runner.py
psutil/tests/test_linux.py
psutil/tests/test_contracts.py
psutil/tests/test_memleaks.py
psutil/tests/__main__.py
psutil/tests/test_testutils.py
psutil/tests/test_process.py
